cpsat_autotune/__init__.py
cpsat_autotune/__main__.py
cpsat_autotune/caching_solver.py
cpsat_autotune/cli.py
cpsat_autotune/cpsat_parameters.py
cpsat_autotune/metrics.py
cpsat_autotune/model_filter.py
cpsat_autotune/model_loading.py
cpsat_autotune/objective.py
cpsat_autotune/parameter_evaluator.py
cpsat_autotune/parameter_space.py
cpsat_autotune/parameters.py
cpsat_autotune/print_result.py
cpsat_autotune/tune.py
cpsat_autotune-0.6.0.dist-info/licenses/LICENSE
cpsat_autotune-0.6.0.dist-info/METADATA
cpsat_autotune-0.6.0.dist-info/WHEEL
cpsat_autotune-0.6.0.dist-info/entry_points.txt
cpsat_autotune-0.6.0.dist-info/top_level.txt
cpsat_autotune-0.6.0.dist-info/RECORD
