Metadata-Version: 2.4
Name: cpsat-autotune
Version: 0.6.0
Summary: A tool to automatically tune the hyperparameters of the OR-Tools' CP-SAT solver.
Author-email: Dominik Krupke <krupked@gmail.com>
Classifier: Programming Language :: Python :: 3
Classifier: License :: OSI Approved :: MIT License
Classifier: Development Status :: 3 - Alpha
Requires-Python: >=3.10
License-File: LICENSE
Requires-Dist: optuna
Requires-Dist: ortools
Requires-Dist: numpy
Requires-Dist: scipy
Requires-Dist: rich
Requires-Dist: click
Dynamic: license-file
